cowley_sro_parameters/__init__.py
cowley_sro_parameters/modifier.py
cowley_sro_parameters-1.1.1.dist-info/licenses/LICENSE
cowley_sro_parameters-1.1.1.dist-info/METADATA
cowley_sro_parameters-1.1.1.dist-info/WHEEL
cowley_sro_parameters-1.1.1.dist-info/top_level.txt
cowley_sro_parameters-1.1.1.dist-info/RECORD
