Metadata-Version: 2.4
Name: cowley_sro_parameters
Version: 1.1.1
Home-page: https://github.com/muexly/cowley_sro_parameters
Author: Jacob Jeffries
Author-email: jwjeffr@clemson.edu
License-File: LICENSE
Dynamic: license-file
